{
    "tag": "h2",
    "text": "AccessoryName.fmg",
    "children": [
        {
            "tag": "h3",
            "text": "緋琥珀のメダリオン",
            "id": "1000",
            "children": [
                {
                    "tag": "p",
                    "text": "緋色の琥珀が嵌めこまれたメダリオン ＨＰの最大値を上昇させる"
                },
                {
                    "tag": "p",
                    "text": "琥珀とは、黄金樹の古い雫であり 最初のエルデの王、ゴッドフレイの時代に特別な宝石として扱われた"
                },
                {
                    "tag": "p",
                    "text": "それは生命の原始的な力を宿している"
                }
            ]
        },
        {
            "tag": "h3",
            "text": "緋琥珀のメダリオン＋１",
            "id": "1001",
            "children": [
                {
                    "tag": "p",
                    "text": "緋色の琥珀が嵌めこまれたメダリオン ＨＰの最大値を大きく上昇させる"
                },
                {
                    "tag": "p",
                    "text": "琥珀とは、黄金樹の古い雫であり 最初のエルデの王、ゴッドフレイの時代に特別な宝石として扱われた"
                },
                {
                    "tag": "p",
                    "text": "それは生命の原始的な力を宿している"
                }
            ]
        },
        {
            "tag": "h3",
            "text": "緋琥珀のメダリオン＋２",
            "id": "1002",
            "children": [
                {
                    "tag": "p",
                    "text": "緋色の琥珀が嵌めこまれたメダリオン ＨＰの最大値を、とても大きく上昇させる"
                },
                {
                    "tag": "p",
                    "text": "琥珀とは、黄金樹の古い雫であり 最初のエルデの王、ゴッドフレイの時代に特別な宝石として扱われた"
                },
                {
                    "tag": "p",
                    "text": "それは生命の原始的な力を宿している"
                }
            ]
        },
        {
            "tag": "h3",
            "text": "青琥珀のメダリオン",
            "id": "1010",
            "children": [
                {
                    "tag": "p",
                    "text": "青色の琥珀が嵌めこまれたメダリオン ＦＰの最大値を上昇させる"
                },
                {
                    "tag": "p",
                    "text": "琥珀とは、黄金樹の古い雫であり 最初のエルデの王、ゴッドフレイの時代に特別な宝石として扱われた"
                },
                {
                    "tag": "p",
                    "text": "それは生命の原始的な力を宿している"
                }
            ]
        },
        {
            "tag": "h3",
            "text": "青琥珀のメダリオン＋１",
            "id": "1011",
            "children": [
                {
                    "tag": "p",
                    "text": "青色の琥珀が嵌めこまれたメダリオン ＦＰの最大値を大きく上昇させる"
                },
                {
                    "tag": "p",
                    "text": "琥珀とは、黄金樹の古い雫であり 最初のエルデの王、ゴッドフレイの時代に特別な宝石として扱われた"
                },
                {
                    "tag": "p",
                    "text": "それは生命の原始的な力を宿している"
                }
            ]
        },
        {
            "tag": "h3",
            "text": "青琥珀のメダリオン＋２",
            "id": "1012",
            "children": [
                {
                    "tag": "p",
                    "text": "青色の琥珀が嵌めこまれたメダリオン ＦＰの最大値を、とても大きく上昇させる"
                },
                {
                    "tag": "p",
                    "text": "琥珀とは、黄金樹の古い雫であり 最初のエルデの王、ゴッドフレイの時代に特別な宝石として扱われた"
                },
                {
                    "tag": "p",
                    "text": "それは生命の原始的な力を宿している"
                }
            ]
        },
        {
            "tag": "h3",
            "text": "緑琥珀のメダリオン",
            "id": "1020",
            "children": [
                {
                    "tag": "p",
                    "text": "緑色の琥珀が嵌めこまれたメダリオン スタミナの最大値を上昇させる"
                },
                {
                    "tag": "p",
                    "text": "琥珀とは、黄金樹の古い雫であり 最初のエルデの王、ゴッドフレイの時代に特別な宝石として扱われた"
                },
                {
                    "tag": "p",
                    "text": "それは生命の原始的な力を宿している"
                }
            ]
        },
        {
            "tag": "h3",
            "text": "緑琥珀のメダリオン＋１",
            "id": "1021",
            "children": [
                {
                    "tag": "p",
                    "text": "緑色の琥珀が嵌めこまれたメダリオン スタミナの最大値を大きく上昇させる"
                },
                {
                    "tag": "p",
                    "text": "琥珀とは、黄金樹の古い雫であり 最初のエルデの王、ゴッドフレイの時代に特別な宝石として扱われた"
                },
                {
                    "tag": "p",
                    "text": "それは生命の原始的な力を宿している"
                }
            ]
        },
        {
            "tag": "h3",
            "text": "緑琥珀のメダリオン＋２",
            "id": "1022",
            "children": [
                {
                    "tag": "p",
                    "text": "緑色の琥珀が嵌めこまれたメダリオン スタミナの最大値を、とても大きく上昇させる"
                },
                {
                    "tag": "p",
                    "text": "琥珀とは、黄金樹の古い雫であり 最初のエルデの王、ゴッドフレイの時代に特別な宝石として扱われた"
                },
                {
                    "tag": "p",
                    "text": "それは生命の原始的な力を宿している"
                }
            ]
        },
        {
            "tag": "h3",
            "text": "武具塊のお守り",
            "id": "1030",
            "children": [
                {
                    "tag": "p",
                    "text": "武具の塊を表した鉄製のお守り 装備重量の上限を上昇させる"
                },
                {
                    "tag": "p",
                    "text": "復讐の英雄の得物として知られる 異形の大剣に由来したタリスマン"
                }
            ]
        },
        {
            "tag": "h3",
            "text": "武具塊のお守り＋１",
            "id": "1031",
            "children": [
                {
                    "tag": "p",
                    "text": "武具の塊を表した鉄製のお守り 装備重量の上限を大きく上昇させる"
                },
                {
                    "tag": "p",
                    "text": "復讐の英雄の得物として知られる 異形の大剣に由来したタリスマン"
                }
            ]
        },
        {
            "tag": "h3",
            "text": "大壺の武具塊",
            "id": "1032",
            "children": [
                {
                    "tag": "p",
                    "text": "大壺に溢れんばかりの武具塊のお守り 装備重量の上限を、とても大きく上昇させる"
                },
                {
                    "tag": "p",
                    "text": "大壺は、自らの戦士たちにこれを授ける いっぱい持って、大きくなれよ"
                }
            ]
        },
        {
            "tag": "h3",
            "text": "黄金樹の恩寵",
            "id": "1040",
            "children": [
                {
                    "tag": "p",
                    "text": "黄金樹の特別な恩寵の象り 最大ＨＰ、スタミナ、最大装備重量を 少しずつ上昇させる"
                },
                {
                    "tag": "p",
                    "text": "黄金樹の時代、そのはじまりにおいて 女王マリカは手ずからそれを与えたという"
                }
            ]
        },
        {
            "tag": "h3",
            "text": "黄金樹の恩寵＋１",
            "id": "1041",
            "children": [
                {
                    "tag": "p",
                    "text": "黄金樹の特別な恩寵の象り 最大ＨＰ、スタミナ、最大装備重量を 上昇させる"
                },
                {
                    "tag": "p",
                    "text": "黄金樹の時代、そのはじまりにおいて 女王マリカは手ずからそれを与えたという"
                }
            ]
        },
        {
            "tag": "h3",
            "text": "黄金樹の恩寵＋２",
            "id": "1042",
            "children": [
                {
                    "tag": "p",
                    "text": "黄金樹の特別な恩寵の象り 「伝説のタリスマン」のひとつ"
                },
                {
                    "tag": "p",
                    "text": "最大ＨＰ、スタミナ、最大装備重量を 大きく上昇させる"
                },
                {
                    "tag": "p",
                    "text": "黄金樹の時代、そのはじまりにおいて 女王マリカは手ずからそれを与えたという"
                }
            ]
        },
        {
            "tag": "h3",
            "text": "ラダゴンの刻印",
            "id": "1050",
            "children": [
                {
                    "tag": "p",
                    "text": "エルデのルーンが刻印された瞳 それは、王配ラダゴンの印であるという"
                },
                {
                    "tag": "p",
                    "text": "生命力、持久力、筋力、技量が高まるが 被ダメージも大きくなる"
                },
                {
                    "tag": "p",
                    "text": "刻印は、神に見出された者が 生涯の使命を与えられた証である"
                }
            ]
        },
        {
            "tag": "h3",
            "text": "ラダゴンの爛れ刻印",
            "id": "1051",
            "children": [
                {
                    "tag": "p",
                    "text": "エルデのルーンが刻印された瞳 「伝説のタリスマン」のひとつそれは、王配ラダゴンの印であるという"
                },
                {
                    "tag": "p",
                    "text": "生命力、持久力、筋力、技量が大きく高まるが 被ダメージもとても大きくなる"
                },
                {
                    "tag": "p",
                    "text": "強き使命は、その主を蝕む まるで逃れ得ぬ呪いのように"
                }
            ]
        },
        {
            "tag": "h3",
            "text": "星砕きの伝承",
            "id": "1060",
            "children": [
                {
                    "tag": "p",
                    "text": "英雄の伝承が刻まれたタリスマン 筋力を高める"
                },
                {
                    "tag": "p",
                    "text": "デミゴッドで最も強いとされた英雄は 降る星に一人で挑み、これを砕き以来、星の運命は封印されたという"
                }
            ]
        },
        {
            "tag": "h3",
            "text": "義手剣士の伝承",
            "id": "1070",
            "children": [
                {
                    "tag": "p",
                    "text": "英雄の伝承が刻まれたタリスマン 技量を高める"
                },
                {
                    "tag": "p",
                    "text": "生まれながら宿痾に侵された少女は 師と、彼の流水の剣と出会い無双の翼を得たという"
                }
            ]
        },
        {
            "tag": "h3",
            "text": "星見少女の伝承",
            "id": "1080",
            "children": [
                {
                    "tag": "p",
                    "text": "女王の伝承が刻まれたタリスマン 知力を高める"
                },
                {
                    "tag": "p",
                    "text": "星見の少女は、夜空を見上げ歩いた ずっとずっと、星を追って旅をしたそして満月と出会い、女王となった"
                }
            ]
        },
        {
            "tag": "h3",
            "text": "二本指の伝承",
            "id": "1090",
            "children": [
                {
                    "tag": "p",
                    "text": "二本指の伝承が刻まれたタリスマン 信仰を高める"
                },
                {
                    "tag": "p",
                    "text": "指は声を持たず、だが雄弁であった 指は執拗に蠢き、空に神秘を綴ったそして我らは言葉を得た。信仰の言葉を"
                }
            ]
        },
        {
            "tag": "h3",
            "text": "銀のスカラベ",
            "id": "1100",
            "children": [
                {
                    "tag": "p",
                    "text": "あらゆる宝、貴重なものの運び手たる スカラベを象ったタリスマン"
                },
                {
                    "tag": "p",
                    "text": "銀色のそれは、発見力を高める"
                }
            ]
        },
        {
            "tag": "h3",
            "text": "金のスカラベ",
            "id": "1110",
            "children": [
                {
                    "tag": "p",
                    "text": "あらゆる宝、貴重なものの運び手たる スカラベを象ったタリスマン"
                },
                {
                    "tag": "p",
                    "text": "金色のそれは、敵を倒したとき 得るルーンの量が増える"
                }
            ]
        },
        {
            "tag": "h3",
            "text": "ノクステラの月",
            "id": "1140",
            "children": [
                {
                    "tag": "p",
                    "text": "永遠の都、ノクステラの秘宝 「伝説のタリスマン」のひとつ"
                },
                {
                    "tag": "p",
                    "text": "記憶スロットを増やす"
                },
                {
                    "tag": "p",
                    "text": "それは、彼らが失くした黒い月を模している ノクステラの月は、無数の星を従えていた"
                }
            ]
        },
        {
            "tag": "h3",
            "text": "緑亀のタリスマン",
            "id": "1150",
            "children": [
                {
                    "tag": "p",
                    "text": "緑色の亀を象ったタリスマン スタミナの回復速度を高める"
                },
                {
                    "tag": "p",
                    "text": "亀は、滋養のある食材として知られ 尽きぬ力の象徴とされた"
                },
                {
                    "tag": "p",
                    "text": "けれど、亀を賢獣と呼ぶ者たちには それは蛮習と映ったという"
                }
            ]
        },
        {
            "tag": "h3",
            "text": "頑健の角飾り",
            "id": "1160",
            "children": [
                {
                    "tag": "p",
                    "text": "祖霊の民の装身具 頑健耐性を高める （頑健は、出血や冷気に対する耐性である）"
                },
                {
                    "tag": "p",
                    "text": "それは、芽生えかけの角であるという 長く生きた獣は、角に新たな芽生えを迎えそれを永遠に繰り返し、いつか祖霊となるのだと"
                }
            ]
        },
        {
            "tag": "h3",
            "text": "頑健の角飾り＋１",
            "id": "1161",
            "children": [
                {
                    "tag": "p",
                    "text": "祖霊の民の装身具 頑健耐性を大きく高める（頑健は、出血や冷気に対する耐性である）"
                },
                {
                    "tag": "p",
                    "text": "それは、芽生えかけの角であるという 長く生きた獣は、角に新たな芽生えを迎えそれを永遠に繰り返し、いつか祖霊となるのだと"
                }
            ]
        },
        {
            "tag": "h3",
            "text": "免疫の角飾り",
            "id": "1170",
            "children": [
                {
                    "tag": "p",
                    "text": "祖霊の民の装身具 免疫耐性を高める （免疫は、毒や腐敗に対する耐性である）"
                },
                {
                    "tag": "p",
                    "text": "それは、芽生えかけの角であるという 長く生きた獣は、角に新たな芽生えを迎えそれを永遠に繰り返し、いつか祖霊となるのだと"
                }
            ]
        },
        {
            "tag": "h3",
            "text": "免疫の角飾り＋１",
            "id": "1171",
            "children": [
                {
                    "tag": "p",
                    "text": "祖霊の民の装身具 免疫耐性を大きく高める （免疫は、毒や腐敗に対する耐性である）"
                },
                {
                    "tag": "p",
                    "text": "それは、芽生えかけの角であるという 長く生きた獣は、角に新たな芽生えを迎えそれを永遠に繰り返し、いつか祖霊となるのだと"
                }
            ]
        },
        {
            "tag": "h3",
            "text": "正気の角飾り",
            "id": "1180",
            "children": [
                {
                    "tag": "p",
                    "text": "祖霊の民の装身具 正気耐性を高める （正気は、睡眠や発狂に対する耐性である）"
                },
                {
                    "tag": "p",
                    "text": "それは、芽生えかけの角であるという 長く生きた獣は、角に新たな芽生えを迎えそれを永遠に繰り返し、いつか祖霊となるのだと"
                }
            ]
        },
        {
            "tag": "h3",
            "text": "正気の角飾り＋１",
            "id": "1181",
            "children": [
                {
                    "tag": "p",
                    "text": "祖霊の民の装身具 正気耐性を大きく高める（正気は、睡眠や発狂に対する耐性である）"
                },
                {
                    "tag": "p",
                    "text": "それは、芽生えかけの角であるという 長く生きた獣は、角に新たな芽生えを迎えそれを永遠に繰り返し、いつか祖霊となるのだと"
                }
            ]
        },
        {
            "tag": "h3",
            "text": "死王子の瘡",
            "id": "1190",
            "children": [
                {
                    "tag": "p",
                    "text": "生臭く膿んだ人面の瘡 抗死耐性を高める"
                },
                {
                    "tag": "p",
                    "text": "その顔の主は、死王子であるという 彼は、かつてゴッドウィンと呼ばれデミゴッド最初の死者として、王都の地下深く 黄金樹の根本に埋葬されたという"
                }
            ]
        },
        {
            "tag": "h3",
            "text": "死王子の業瘡",
            "id": "1191",
            "children": [
                {
                    "tag": "p",
                    "text": "生臭く膿んだ人面の業瘡 抗死耐性を大きく高める"
                },
                {
                    "tag": "p",
                    "text": "その顔の主は、死王子であるという デミゴッド最初の死者たる黄金の貴公子の死にきれず、穢れきった死に顔であるという"
                }
            ]
        },
        {
            "tag": "h3",
            "text": "斑色の首飾り",
            "id": "1200",
            "children": [
                {
                    "tag": "p",
                    "text": "祖霊の民の装身具 その、特に彩られた貴重なもの"
                },
                {
                    "tag": "p",
                    "text": "免疫、頑健、正気の耐性を高める"
                },
                {
                    "tag": "p",
                    "text": "それは、芽生えかけの角であるという 長く生きた獣は、角に新たな芽生えを迎えそれを永遠に繰り返し、いつか祖霊となるのだと"
                }
            ]
        },
        {
            "tag": "h3",
            "text": "斑色の首飾り＋１",
            "id": "1201",
            "children": [
                {
                    "tag": "p",
                    "text": "祖霊の民の装身具 その、特に彩られた貴重なもの"
                },
                {
                    "tag": "p",
                    "text": "免疫、頑健、正気の耐性を大きく高める"
                },
                {
                    "tag": "p",
                    "text": "それは、芽生えかけの角であるという 長く生きた獣は、角に新たな芽生えを迎えそれを永遠に繰り返し、いつか祖霊となるのだと"
                }
            ]
        },
        {
            "tag": "h3",
            "text": "大山羊のタリスマン",
            "id": "1210",
            "children": [
                {
                    "tag": "p",
                    "text": "大山羊の角を象ったタリスマン 強靭度を高める"
                },
                {
                    "tag": "p",
                    "text": "大山羊は、ある騎士の名で知られる 太く、強く、決して怯まぬトラゴスは戦う者の、物言わぬ友であるという"
                }
            ]
        },
        {
            "tag": "h3",
            "text": "マリカの刻印",
            "id": "1220",
            "children": [
                {
                    "tag": "p",
                    "text": "エルデのルーンが刻印された瞳 それは、女王マリカの印であるという"
                },
                {
                    "tag": "p",
                    "text": "精神力、知力、信仰、神秘が高まるが 被ダメージも大きくなる"
                },
                {
                    "tag": "p",
                    "text": "刻印は、神に見出された者が 生涯の使命を与えられた証である"
                }
            ]
        },
        {
            "tag": "h3",
            "text": "マリカの爛れ刻印",
            "id": "1221",
            "children": [
                {
                    "tag": "p",
                    "text": "エルデのルーンが刻印された瞳 「伝説のタリスマン」のひとつそれは、女王マリカの印であるという"
                },
                {
                    "tag": "p",
                    "text": "精神力、知力、信仰、神秘が大きく高まるが 被ダメージもとても大きくなる"
                },
                {
                    "tag": "p",
                    "text": "強き使命は、その主を蝕む まるで逃れ得ぬ呪いのように"
                }
            ]
        },
        {
            "tag": "h3",
            "text": "戦士の壺の破片",
            "id": "1230",
            "children": [
                {
                    "tag": "p",
                    "text": "壊れて死んだ、戦士の壺の破片"
                },
                {
                    "tag": "p",
                    "text": "戦技の攻撃力を高める"
                },
                {
                    "tag": "p",
                    "text": "蕩けた屍肉が破片にこびり付き その内には、装飾品の名残が見て取れる古い、王族の戦士の遺品だろう"
                }
            ]
        },
        {
            "tag": "h3",
            "text": "アレキサンダーの破片",
            "id": "1231",
            "children": [
                {
                    "tag": "p",
                    "text": "壊れて死んだ 戦士の壺、アレキサンダーの破片"
                },
                {
                    "tag": "p",
                    "text": "戦技の攻撃力を大きく高める"
                },
                {
                    "tag": "p",
                    "text": "蕩けた屍肉が破片にこびり付き その内には、装飾品の名残が見て取れる赤髪の英雄の遺品のようだ"
                }
            ]
        },
        {
            "tag": "h3",
            "text": "ミリセントの義手",
            "id": "1250",
            "children": [
                {
                    "tag": "p",
                    "text": "ミリセントが用いた黄金の義手の一部 剣を掲げる形で固まった掌"
                },
                {
                    "tag": "p",
                    "text": "技量を高め 攻撃が連続するほど、攻撃力を高める"
                },
                {
                    "tag": "p",
                    "text": "素晴らしき裏切りの絶望により 蕾たる彼女は、色めく花となったそして、いつか再誕するだろう 美しき、朱い戦乙女となって"
                }
            ]
        },
        {
            "tag": "h3",
            "text": "魔力の蠍",
            "id": "2000",
            "children": [
                {
                    "tag": "p",
                    "text": "奇手奇襲の刺客たちのタリスマン 脱皮直後の蠍が模され、その鋏は魔力色の心臓を捕らえている"
                },
                {
                    "tag": "p",
                    "text": "魔力攻撃力を高めるが カット率が下がってしまう"
                }
            ]
        },
        {
            "tag": "h3",
            "text": "雷の蠍",
            "id": "2010",
            "children": [
                {
                    "tag": "p",
                    "text": "奇手奇襲の刺客たちのタリスマン 脱皮直後の蠍が模され、その鋏は雷色の心臓を捕らえている"
                },
                {
                    "tag": "p",
                    "text": "雷攻撃力を高めるが カット率が下がってしまう"
                }
            ]
        },
        {
            "tag": "h3",
            "text": "炎の蠍",
            "id": "2020",
            "children": [
                {
                    "tag": "p",
                    "text": "奇手奇襲の刺客たちのタリスマン 脱皮直後の蠍が模され、その鋏は炎色の心臓を捕らえている"
                },
                {
                    "tag": "p",
                    "text": "炎攻撃力を高めるが カット率が下がってしまう"
                }
            ]
        },
        {
            "tag": "h3",
            "text": "聖なる蠍",
            "id": "2030",
            "children": [
                {
                    "tag": "p",
                    "text": "奇手奇襲の刺客たちのタリスマン 脱皮直後の蠍が模され、その鋏は聖色の心臓を捕らえている"
                },
                {
                    "tag": "p",
                    "text": "聖攻撃力を高めるが カット率が下がってしまう"
                }
            ]
        },
        {
            "tag": "h3",
            "text": "赤羽の七支刃",
            "id": "2040",
            "children": [
                {
                    "tag": "p",
                    "text": "古代の死儀礼に由来するタリスマン 赤羽のそれは、ＨＰが減少したとき攻撃力を高める"
                },
                {
                    "tag": "p",
                    "text": "死に近付くは高揚である それでこそ、懸命に生に縋り付き 後の死はより輝かしい"
                }
            ]
        },
        {
            "tag": "h3",
            "text": "捧闘の剣のタリスマン",
            "id": "2050",
            "children": [
                {
                    "tag": "p",
                    "text": "かつて黄金樹に捧げられた闘いの 儀式の剣を模したタリスマン"
                },
                {
                    "tag": "p",
                    "text": "ＨＰが最大のとき、攻撃力を高める"
                },
                {
                    "tag": "p",
                    "text": "王配ラダゴンの時代、捧闘は廃れてしまった 各地に残る闘技場は、その名残である"
                }
            ]
        },
        {
            "tag": "h3",
            "text": "槍のタリスマン",
            "id": "2060",
            "children": [
                {
                    "tag": "p",
                    "text": "槍と兵士を象ったタリスマン 刺突攻撃特有の、カウンター攻撃を強化する"
                },
                {
                    "tag": "p",
                    "text": "槍は、狭間の地の兵士の一般的な武器であり ときに強者に、手痛い反撃をあたえた"
                }
            ]
        },
        {
            "tag": "h3",
            "text": "大槌のタリスマン",
            "id": "2070",
            "children": [
                {
                    "tag": "p",
                    "text": "大槌と騎士を象ったタリスマン ガードに対するスタミナ攻撃力を強化する"
                },
                {
                    "tag": "p",
                    "text": "槌は、盾を用いる敵に効果が高く 故に騎士狩りの武器として知られている"
                }
            ]
        },
        {
            "tag": "h3",
            "text": "有翼剣の徽章",
            "id": "2080",
            "children": [
                {
                    "tag": "p",
                    "text": "掲げられた義手刀を象ったタリスマン 欠け身のマレニアと、共に戦った騎士たちの徽章"
                },
                {
                    "tag": "p",
                    "text": "攻撃が連続するほど、攻撃力が高まる"
                },
                {
                    "tag": "p",
                    "text": "翼はマレニアと、その不敗の戦の象徴である 生来の宿痾により癒しを知らぬ彼女の剣は 美しく、ただ熾烈であり続けた"
                }
            ]
        },
        {
            "tag": "h3",
            "text": "腐敗翼剣の徽章",
            "id": "2081",
            "children": [
                {
                    "tag": "p",
                    "text": "掲げられた義手刀を象ったタリスマン 腐敗の女神に仕える、戦乙女たちの徽章"
                },
                {
                    "tag": "p",
                    "text": "攻撃が連続するほど、攻撃力が大きく高まる"
                },
                {
                    "tag": "p",
                    "text": "四姉妹は、エオニアの沼に生まれ落ち ゴーリーの手引きにより、聖樹へと至っただが彼女たちは、出来損ないの蕾であった"
                }
            ]
        },
        {
            "tag": "h3",
            "text": "短剣のタリスマン",
            "id": "2090",
            "children": [
                {
                    "tag": "p",
                    "text": "短剣と医師を象ったタリスマン 致命の一撃を強化する"
                },
                {
                    "tag": "p",
                    "text": "白衣の戦場医師は、敵味方に関わらず 死に損なった者たちを一突きで介錯するまさに慈悲こそが、殺意を高めるのだ"
                }
            ]
        },
        {
            "tag": "h3",
            "text": "遠矢のタリスマン",
            "id": "2100",
            "children": [
                {
                    "tag": "p",
                    "text": "三本の羽矢を象ったタリスマン 獣を狩る、狩人たちのもの"
                },
                {
                    "tag": "p",
                    "text": "弓の飛距離が上昇する"
                }
            ]
        },
        {
            "tag": "h3",
            "text": "青い踊り子",
            "id": "2110",
            "children": [
                {
                    "tag": "p",
                    "text": "青衣の踊り子を象った布人形 とても古い、伝承の遺物"
                },
                {
                    "tag": "p",
                    "text": "装備重量が少ないほど、攻撃力が高まる"
                },
                {
                    "tag": "p",
                    "text": "青衣の踊り子は、妖精であったという 妖精は、盲目の剣士に流水の剣を授け古き神、腐敗を封じたと伝わっている"
                }
            ]
        },
        {
            "tag": "h3",
            "text": "両刃のタリスマン",
            "id": "2120",
            "children": [
                {
                    "tag": "p",
                    "text": "両刃剣と密使を象ったタリスマン 連撃の最終攻撃を強化する"
                },
                {
                    "tag": "p",
                    "text": "密使たちに伝わる両刃の剣技は 攻撃の勢いを殺さないことを、極意とする故にその最終攻撃は、危険である"
                }
            ]
        },
        {
            "tag": "h3",
            "text": "斧のタリスマン",
            "id": "2130",
            "children": [
                {
                    "tag": "p",
                    "text": "斧と戦士を象ったタリスマン タメ攻撃を強化する"
                },
                {
                    "tag": "p",
                    "text": "斧は、長征の戦王の武器である 王を誇る戦士たちは、同じ武器を振るい力を込めた一撃に長けている"
                }
            ]
        },
        {
            "tag": "h3",
            "text": "ランスのタリスマン",
            "id": "2140",
            "children": [
                {
                    "tag": "p",
                    "text": "ランスと騎馬騎士を象ったタリスマン 馬上での攻撃力を強化する"
                },
                {
                    "tag": "p",
                    "text": "馬上にある騎士は、恐ろしい 高きによって低きを視るは 勢いすでに破竹であろう"
                }
            ]
        },
        {
            "tag": "h3",
            "text": "硬矢のタリスマン",
            "id": "2150",
            "children": [
                {
                    "tag": "p",
                    "text": "三本の鉄矢を象ったタリスマン 古い兵士たちのもの"
                },
                {
                    "tag": "p",
                    "text": "矢やボルトによる射撃の 攻撃力が高まる"
                }
            ]
        },
        {
            "tag": "h3",
            "text": "血の君主の歓喜",
            "id": "2160",
            "children": [
                {
                    "tag": "p",
                    "text": "血の君主の喜びを模したタリスマン"
                },
                {
                    "tag": "p",
                    "text": "周囲で出血状態が発生すると、攻撃力が高まる"
                },
                {
                    "tag": "p",
                    "text": "血の君主に、血を捧げよ 御方の閨を、繭を血で満たせ幼き伴侶が目覚める時、我ら王朝開闢せん"
                }
            ]
        },
        {
            "tag": "h3",
            "text": "腐敗眷属の歓喜",
            "id": "2170",
            "children": [
                {
                    "tag": "p",
                    "text": "蟲たちの喜びを模したタリスマン"
                },
                {
                    "tag": "p",
                    "text": "周囲で毒あるいは腐敗状態が発生すると 攻撃力が高まる"
                },
                {
                    "tag": "p",
                    "text": "朱の女神に、腐敗を捧げよ 遠い彼方で、朱い花咲誇り 我ら落とし子に戻りたまえ"
                }
            ]
        },
        {
            "tag": "h3",
            "text": "爪のタリスマン",
            "id": "2180",
            "children": [
                {
                    "tag": "p",
                    "text": "爪と凶手を象ったタリスマン ジャンプ攻撃を強化する"
                },
                {
                    "tag": "p",
                    "text": "暗殺を生業とする、カラス山の凶手たちは 自らを死の猛禽に擬し、獲物に襲いかかる"
                }
            ]
        },
        {
            "tag": "h3",
            "text": "咆哮のメダリオン",
            "id": "2190",
            "children": [
                {
                    "tag": "p",
                    "text": "叫ぶ巨人を象った、青銅のメダリオン 咆哮とブレスを強化する"
                },
                {
                    "tag": "p",
                    "text": "古い時代、巨人は黄金樹の宿敵であった その轟く咆哮は大自然を荒ぶらせ雪崩をおこし、炎を嵐としたという"
                }
            ]
        },
        {
            "tag": "h3",
            "text": "曲剣のタリスマン",
            "id": "2200",
            "children": [
                {
                    "tag": "p",
                    "text": "曲剣と剣士を象ったタリスマン ガードカウンターを強化する"
                },
                {
                    "tag": "p",
                    "text": "肉を切らせて骨を断つ、その卓越した剣技は かつて盲目の剣士が見出したという"
                }
            ]
        },
        {
            "tag": "h3",
            "text": "友なる壺",
            "id": "2210",
            "children": [
                {
                    "tag": "p",
                    "text": "壺たちが、友に贈るタリスマン 投擲壺アイテムの威力を高める"
                },
                {
                    "tag": "p",
                    "text": "人の血肉を、その生の源としながらも 壺たちは皆善良である。あるいはそれこそが彼らが作られた理由であったろうか"
                }
            ]
        },
        {
            "tag": "h3",
            "text": "調香師のタリスマン",
            "id": "2220",
            "children": [
                {
                    "tag": "p",
                    "text": "調香瓶を模したタリスマン 調香アイテムの威力を高める"
                },
                {
                    "tag": "p",
                    "text": "調香師には、彼らだけが知る花園がある 高原の辺縁に、あるいは隠された洞窟にそこで花々は、ただ香るためだけに咲く"
                }
            ]
        },
        {
            "tag": "h3",
            "text": "魔術師球のタリスマン",
            "id": "3000",
            "children": [
                {
                    "tag": "p",
                    "text": "魔術師球と呼ばれる 学院の悪夢を象ったタリスマン"
                },
                {
                    "tag": "p",
                    "text": "魔術の威力を高める"
                },
                {
                    "tag": "p",
                    "text": "輝石魔術には、源流という禁忌がある 魔術師を集めて星の種となす源流では、これは探究の一手段なのだ"
                }
            ]
        },
        {
            "tag": "h3",
            "text": "魔術師塊のタリスマン",
            "id": "3001",
            "children": [
                {
                    "tag": "p",
                    "text": "魔術師球と呼ばれる学院の悪夢 最初のそれを象ったタリスマン"
                },
                {
                    "tag": "p",
                    "text": "魔術の威力を大きく高める"
                },
                {
                    "tag": "p",
                    "text": "輝石魔術には、源流という禁忌がある 魔術師を集めて星の種となす源流では、これは探究の一手段なのだ"
                }
            ]
        },
        {
            "tag": "h3",
            "text": "信徒の誓布",
            "id": "3040",
            "children": [
                {
                    "tag": "p",
                    "text": "仮面の偶像が描かれた布きれ 祈祷の威力を高める"
                },
                {
                    "tag": "p",
                    "text": "その偶像は信徒を模している 形無きものを頑なに信じ、祈る様は孤独な教祖にすら勇気を与える"
                },
                {
                    "tag": "p",
                    "text": "信仰とは、つまり肯定であろう"
                }
            ]
        },
        {
            "tag": "h3",
            "text": "集う信徒の誓布",
            "id": "3050",
            "children": [
                {
                    "tag": "p",
                    "text": "大量の偶像が描かれた布きれ 祈祷の威力を大きく高める"
                },
                {
                    "tag": "p",
                    "text": "その偶像は信徒を模している 形無きものを頑なに信じ、祈る様は孤独な教祖にすら勇気を与える"
                },
                {
                    "tag": "p",
                    "text": "信仰とは、つまり肯定であろう"
                }
            ]
        },
        {
            "tag": "h3",
            "text": "古き王のタリスマン",
            "id": "3060",
            "children": [
                {
                    "tag": "p",
                    "text": "時の狭間、嵐の中心に座すという 古き王を象ったタリスマン「伝説のタリスマン」のひとつ"
                },
                {
                    "tag": "p",
                    "text": "魔術と祈祷の効果時間を延ばす"
                },
                {
                    "tag": "p",
                    "text": "古き王の都、ファルム・アズラは 遥か前からずっと ゆっくりと崩壊しているという"
                }
            ]
        },
        {
            "tag": "h3",
            "text": "ラダゴンの肖像",
            "id": "3070",
            "children": [
                {
                    "tag": "p",
                    "text": "エルデの王、ラダゴンを象ったタリスマン 「伝説のタリスマン」のひとつ"
                },
                {
                    "tag": "p",
                    "text": "魔術と祈祷の使用速度を速める"
                },
                {
                    "tag": "p",
                    "text": "赤髪のラダゴンは カーリアのレナラの夫として魔術を修め女王マリカの夫として祈祷を修めたという 英雄は、完全たるを目指したのだ"
                }
            ]
        },
        {
            "tag": "h3",
            "text": "原輝石の刃",
            "id": "3080",
            "children": [
                {
                    "tag": "p",
                    "text": "血濡れた古い輝石の刃"
                },
                {
                    "tag": "p",
                    "text": "魔術と祈祷の消費ＦＰが少なくなるが 最大ＨＰも減ってしまう"
                },
                {
                    "tag": "p",
                    "text": "原輝石を、自らの魂とするために 古い魔術師は、この刃で心臓を切り裂くそしてそのまま死んでいく"
                }
            ]
        },
        {
            "tag": "h3",
            "text": "ゴッドフレイの肖像",
            "id": "3090",
            "children": [
                {
                    "tag": "p",
                    "text": "エルデの王、ゴッドフレイを象ったタリスマン 「伝説のタリスマン」のひとつ"
                },
                {
                    "tag": "p",
                    "text": "魔術／祈祷／戦技のタメ使用を強化する"
                },
                {
                    "tag": "p",
                    "text": "ゴッドフレイは、猛き戦士であった けれど、王となるを誓ったとき沸々と滾り続ける戦意を抑えるため 宰相の獣、セローシュを背負ったのだ"
                }
            ]
        },
        {
            "tag": "h3",
            "text": "竜印の盾のタリスマン",
            "id": "4000",
            "children": [
                {
                    "tag": "p",
                    "text": "古竜が浮き彫られた、錬鉄のタリスマン 物理カット率を高める"
                },
                {
                    "tag": "p",
                    "text": "黄金樹なき先史時代の主たる古竜は 王を守る、巌の壁であったという故に竜姿は、あらゆる護りの象徴である"
                }
            ]
        },
        {
            "tag": "h3",
            "text": "竜印の盾のタリスマン＋１",
            "id": "4001",
            "children": [
                {
                    "tag": "p",
                    "text": "二体の古竜が浮き彫られた、錬鉄のタリスマン 物理カット率を大きく高める"
                },
                {
                    "tag": "p",
                    "text": "黄金樹なき先史時代の主たる古竜は 王を守る、巌の壁であったという故に竜姿は、あらゆる護りの象徴である"
                }
            ]
        },
        {
            "tag": "h3",
            "text": "竜印の盾のタリスマン＋２",
            "id": "4002",
            "children": [
                {
                    "tag": "p",
                    "text": "三体の古竜が浮き彫られた、錬鉄のタリスマン 物理カット率を、とても大きく高める"
                },
                {
                    "tag": "p",
                    "text": "黄金樹なき先史時代の主たる古竜は 王を守る、巌の壁であったという故に竜姿は、あらゆる護りの象徴である"
                }
            ]
        },
        {
            "tag": "h3",
            "text": "竜印の大盾のタリスマン",
            "id": "4003",
            "children": [
                {
                    "tag": "p",
                    "text": "巨大な古竜が浮き彫られた、錬鉄のタリスマン 「伝説のタリスマン」のひとつ"
                },
                {
                    "tag": "p",
                    "text": "物理カット率を、きわめて大きく高める"
                },
                {
                    "tag": "p",
                    "text": "黄金樹なき先史時代の主たる古竜は 王を守る、巌の壁であったという故に竜姿は、あらゆる護りの象徴である"
                }
            ]
        },
        {
            "tag": "h3",
            "text": "魔力竜印のタリスマン",
            "id": "4010",
            "children": [
                {
                    "tag": "p",
                    "text": "青い古竜の描かれたタリスマン 魔力カット率を高める"
                },
                {
                    "tag": "p",
                    "text": "黄金樹なき先史時代の主たる古竜は 王を守る、巌の壁であったという故に竜姿は、あらゆる護りの象徴である"
                }
            ]
        },
        {
            "tag": "h3",
            "text": "魔力竜印のタリスマン＋１",
            "id": "4011",
            "children": [
                {
                    "tag": "p",
                    "text": "二体の青い古竜の描かれたタリスマン 魔力カット率を大きく高める"
                },
                {
                    "tag": "p",
                    "text": "黄金樹なき先史時代の主たる古竜は 王を守る、巌の壁であったという故に竜姿は、あらゆる護りの象徴である"
                }
            ]
        },
        {
            "tag": "h3",
            "text": "魔力竜印のタリスマン＋２",
            "id": "4012",
            "children": [
                {
                    "tag": "p",
                    "text": "三体の青い古竜の描かれたタリスマン 魔力カット率を、とても大きく高める"
                },
                {
                    "tag": "p",
                    "text": "黄金樹なき先史時代の主たる古竜は 王を守る、巌の壁であったという故に竜姿は、あらゆる護りの象徴である"
                }
            ]
        },
        {
            "tag": "h3",
            "text": "炎竜印のタリスマン",
            "id": "4020",
            "children": [
                {
                    "tag": "p",
                    "text": "赤い古竜の描かれたタリスマン 炎カット率を高める"
                },
                {
                    "tag": "p",
                    "text": "黄金樹なき先史時代の主たる古竜は 王を守る、巌の壁であったという故に竜姿は、あらゆる護りの象徴である"
                }
            ]
        },
        {
            "tag": "h3",
            "text": "炎竜印のタリスマン＋１",
            "id": "4021",
            "children": [
                {
                    "tag": "p",
                    "text": "二体の赤い古竜の描かれたタリスマン 炎カット率を大きく高める"
                },
                {
                    "tag": "p",
                    "text": "黄金樹なき先史時代の主たる古竜は 王を守る、巌の壁であったという故に竜姿は、あらゆる護りの象徴である"
                }
            ]
        },
        {
            "tag": "h3",
            "text": "炎竜印のタリスマン＋２",
            "id": "4022",
            "children": [
                {
                    "tag": "p",
                    "text": "三体の赤い古竜の描かれたタリスマン 炎カット率を、とても大きく高める"
                },
                {
                    "tag": "p",
                    "text": "黄金樹なき先史時代の主たる古竜は 王を守る、巌の壁であったという故に竜姿は、あらゆる護りの象徴である"
                }
            ]
        },
        {
            "tag": "h3",
            "text": "雷竜印のタリスマン",
            "id": "4030",
            "children": [
                {
                    "tag": "p",
                    "text": "黄色い古竜の描かれたタリスマン 雷カット率を高める"
                },
                {
                    "tag": "p",
                    "text": "黄金樹なき先史時代の主たる古竜は 王を守る、巌の壁であったという故に竜姿は、あらゆる護りの象徴である"
                }
            ]
        },
        {
            "tag": "h3",
            "text": "雷竜印のタリスマン＋１",
            "id": "4031",
            "children": [
                {
                    "tag": "p",
                    "text": "二体の黄色い古竜の描かれたタリスマン 雷カット率を大きく高める"
                },
                {
                    "tag": "p",
                    "text": "黄金樹なき先史時代の主たる古竜は 王を守る、巌の壁であったという故に竜姿は、あらゆる護りの象徴である"
                }
            ]
        },
        {
            "tag": "h3",
            "text": "雷竜印のタリスマン＋２",
            "id": "4032",
            "children": [
                {
                    "tag": "p",
                    "text": "三体の黄色い古竜の描かれたタリスマン 雷カット率を、とても大きく高める"
                },
                {
                    "tag": "p",
                    "text": "黄金樹なき先史時代の主たる古竜は 王を守る、巌の壁であったという故に竜姿は、あらゆる護りの象徴である"
                }
            ]
        },
        {
            "tag": "h3",
            "text": "聖竜印のタリスマン",
            "id": "4040",
            "children": [
                {
                    "tag": "p",
                    "text": "金の古竜の描かれたタリスマン 聖カット率を高める"
                },
                {
                    "tag": "p",
                    "text": "黄金樹なき先史時代の主たる古竜は 王を守る、巌の壁であったという故に竜姿は、あらゆる護りの象徴である"
                }
            ]
        },
        {
            "tag": "h3",
            "text": "聖竜印のタリスマン＋１",
            "id": "4041",
            "children": [
                {
                    "tag": "p",
                    "text": "二体の金の古竜の描かれたタリスマン 聖カット率を大きく高める"
                },
                {
                    "tag": "p",
                    "text": "黄金樹なき先史時代の主たる古竜は 王を守る、巌の壁であったという故に竜姿は、あらゆる護りの象徴である"
                }
            ]
        },
        {
            "tag": "h3",
            "text": "聖竜印のタリスマン＋２",
            "id": "4042",
            "children": [
                {
                    "tag": "p",
                    "text": "三体の金の古竜の描かれたタリスマン 聖カット率を、とても大きく高める"
                },
                {
                    "tag": "p",
                    "text": "黄金樹なき先史時代の主たる古竜は 王を守る、巌の壁であったという故に竜姿は、あらゆる護りの象徴である"
                }
            ]
        },
        {
            "tag": "h3",
            "text": "真珠竜印のタリスマン",
            "id": "4050",
            "children": [
                {
                    "tag": "p",
                    "text": "真珠色の古竜の描かれたタリスマン 物理以外のカット率を高める"
                },
                {
                    "tag": "p",
                    "text": "黄金樹なき先史時代の主たる古竜は 王を守る、巌の壁であったという故に竜姿は、あらゆる護りの象徴である"
                }
            ]
        },
        {
            "tag": "h3",
            "text": "真珠竜印のタリスマン＋１",
            "id": "4051",
            "children": [
                {
                    "tag": "p",
                    "text": "二体の真珠色の古竜の描かれたタリスマン 物理以外のカット率を大きく高める"
                },
                {
                    "tag": "p",
                    "text": "黄金樹なき先史時代の主たる古竜は 王を守る、巌の壁であったという故に竜姿は、あらゆる護りの象徴である"
                }
            ]
        },
        {
            "tag": "h3",
            "text": "真珠竜印のタリスマン＋２",
            "id": "4052",
            "children": [
                {
                    "tag": "p",
                    "text": "三体の真珠色の古竜の描かれたタリスマン 物理以外のカット率を、とても大きく高める"
                },
                {
                    "tag": "p",
                    "text": "黄金樹なき先史時代の主たる古竜は 王を守る、巌の壁であったという故に竜姿は、あらゆる護りの象徴である"
                }
            ]
        },
        {
            "tag": "h3",
            "text": "坩堝鱗のタリスマン",
            "id": "4060",
            "children": [
                {
                    "tag": "p",
                    "text": "古い時代、人の身体に生じたという 諸相の混ざった鱗のタリスマン"
                },
                {
                    "tag": "p",
                    "text": "致命の一撃のダメージを軽減する"
                },
                {
                    "tag": "p",
                    "text": "それは、生命の原初たる坩堝の名残である 部分的な先祖返りであり、古くは神聖視されたが 文明の後には穢れとして扱われた"
                }
            ]
        },
        {
            "tag": "h3",
            "text": "坩堝羽のタリスマン",
            "id": "4070",
            "children": [
                {
                    "tag": "p",
                    "text": "古い時代、人の身体に生じたという 諸相の混ざった羽のタリスマン"
                },
                {
                    "tag": "p",
                    "text": "ローリングの回避を強化するが 常に、被ダメージも大きくなる"
                },
                {
                    "tag": "p",
                    "text": "それは、生命の原初たる坩堝の名残である 部分的な先祖返りであり、古くは神聖視されたが 文明の後には穢れとして扱われた"
                }
            ]
        },
        {
            "tag": "h3",
            "text": "青羽の七支刃",
            "id": "4080",
            "children": [
                {
                    "tag": "p",
                    "text": "古代の死儀礼に由来するタリスマン 青羽のそれは、ＨＰが減少したとき防御力を高める"
                },
                {
                    "tag": "p",
                    "text": "死に近付くは高揚である それでこそ、懸命に生に縋り付き 捧げるべき死が生まれる"
                }
            ]
        },
        {
            "tag": "h3",
            "text": "捧闘の盾のタリスマン",
            "id": "4090",
            "children": [
                {
                    "tag": "p",
                    "text": "かつて黄金樹に捧げられた闘いの 儀式の盾を模したタリスマン"
                },
                {
                    "tag": "p",
                    "text": "ＨＰが最大のとき、防御力を高める"
                },
                {
                    "tag": "p",
                    "text": "王配ラダゴンの時代、捧闘は廃れてしまった 各地に残る闘技場は、その名残である"
                }
            ]
        },
        {
            "tag": "h3",
            "text": "大盾のタリスマン",
            "id": "4100",
            "children": [
                {
                    "tag": "p",
                    "text": "大盾と騎士を象ったタリスマン ガード強度を高める"
                },
                {
                    "tag": "p",
                    "text": "かつて、ローデイルの騎士たちは ツリーガードのあり様を範とした守るべきもののために、剣より先に まず盾を構えたのだ"
                }
            ]
        },
        {
            "tag": "h3",
            "text": "坩堝瘤のタリスマン",
            "id": "4110",
            "children": [
                {
                    "tag": "p",
                    "text": "古い時代、人の身体に生じたという 諸相の混ざった瘤のタリスマン"
                },
                {
                    "tag": "p",
                    "text": "ヘッドショットのダメージと、衝撃を軽減する"
                },
                {
                    "tag": "p",
                    "text": "それは、生命の原初たる坩堝の名残である 部分的な先祖返りであり、古くは神聖視されたが 文明の後には穢れとして扱われた"
                }
            ]
        },
        {
            "tag": "h3",
            "text": "緋色種子のタリスマン",
            "id": "5000",
            "children": [
                {
                    "tag": "p",
                    "text": "黄金樹の種子を模した、緋色のタリスマン 緋雫の聖杯瓶の回復量を高める"
                },
                {
                    "tag": "p",
                    "text": "かつて黄金樹は、永遠にして完全であった 故にその種子は、存在しないとされていた"
                }
            ]
        },
        {
            "tag": "h3",
            "text": "青色種子のタリスマン",
            "id": "5010",
            "children": [
                {
                    "tag": "p",
                    "text": "黄金樹の種子を模した、青色のタリスマン 青雫の聖杯瓶の回復量を高める"
                },
                {
                    "tag": "p",
                    "text": "かつて黄金樹は、永遠にして完全であった 故にその種子は、存在しないとされていた"
                }
            ]
        },
        {
            "tag": "h3",
            "text": "恵みの雫のタリスマン",
            "id": "5020",
            "children": [
                {
                    "tag": "p",
                    "text": "黄金樹の恵みたる雫 その受領の様を模したタリスマン"
                },
                {
                    "tag": "p",
                    "text": "ＨＰをゆっくりと回復する"
                },
                {
                    "tag": "p",
                    "text": "かつて、恵みの雫は尽きぬ滴りであったという 豊穣の時代、けれどそれはごく短く黄金樹は信仰となっていった"
                }
            ]
        },
        {
            "tag": "h3",
            "text": "略奪のカメオ",
            "id": "5030",
            "children": [
                {
                    "tag": "p",
                    "text": "火山館の主、法務官ライカードの 厳格な肖像が刻まれたタリスマン"
                },
                {
                    "tag": "p",
                    "text": "敵を倒したとき、ＨＰを回復する"
                },
                {
                    "tag": "p",
                    "text": "ライカードが背律の冒涜を誓ったとき あらゆる略奪は肯定された神自身がそうであるように"
                }
            ]
        },
        {
            "tag": "h3",
            "text": "神肌のおくるみ",
            "id": "5040",
            "children": [
                {
                    "tag": "p",
                    "text": "すべやかな肌を縫い合わせた 神肌の使徒たちの聖布"
                },
                {
                    "tag": "p",
                    "text": "攻撃が連続すると、ＨＰを回復する"
                },
                {
                    "tag": "p",
                    "text": "産まれたばかりの使徒は これに包まれ、宵眼の女王に抱かれるそして神の死となるのだ"
                }
            ]
        },
        {
            "tag": "h3",
            "text": "緋色の凶刃",
            "id": "5050",
            "children": [
                {
                    "tag": "p",
                    "text": "緋色に染まった、捻じくれた凶刃 致命の一撃によりＨＰを回復する"
                },
                {
                    "tag": "p",
                    "text": "それは、かつて陰謀の夜に閃き デミゴッドに最初の死をもたらした黒き刃の似姿である"
                }
            ]
        },
        {
            "tag": "h3",
            "text": "青色の凶刃",
            "id": "5060",
            "children": [
                {
                    "tag": "p",
                    "text": "青色に染まった、捻じくれた凶刃 致命の一撃によりＦＰを回復する"
                },
                {
                    "tag": "p",
                    "text": "それは、かつて陰謀の夜に閃き デミゴッドに最初の死をもたらした黒き刃の似姿である"
                }
            ]
        },
        {
            "tag": "h3",
            "text": "クレプスの小瓶",
            "id": "6000",
            "children": [
                {
                    "tag": "p",
                    "text": "暗闇の霧を封じた神秘の小瓶"
                },
                {
                    "tag": "p",
                    "text": "装備者の立てる音を完全に消す"
                },
                {
                    "tag": "p",
                    "text": "円卓の暗部が用いたという呪具 かつて、導きを外れた褪せ人は 静寂に怯えていた"
                }
            ]
        },
        {
            "tag": "h3",
            "text": "身隠しのヴェール",
            "id": "6010",
            "children": [
                {
                    "tag": "p",
                    "text": "光沢のある暗い布を纏めたタリスマン"
                },
                {
                    "tag": "p",
                    "text": "敵から離れていれば しゃがんだ状態で、装備者の姿を完全に消す"
                },
                {
                    "tag": "p",
                    "text": "かつて、黒き刃の刺客たちが 陰謀の夜にその姿を隠したヴェールの一部"
                }
            ]
        },
        {
            "tag": "h3",
            "text": "カーリアの徽章",
            "id": "6020",
            "children": [
                {
                    "tag": "p",
                    "text": "盾に王家の紋章を象ったタリスマン"
                },
                {
                    "tag": "p",
                    "text": "戦技の消費ＦＰが少なくなる"
                },
                {
                    "tag": "p",
                    "text": "かつて、カーリア騎士の中でも 王女の直参に与えられたという徽章当代の王女は唯一人、レナラの娘、ラニである"
                }
            ]
        },
        {
            "tag": "h3",
            "text": "長尾猫のタリスマン",
            "id": "6040",
            "children": [
                {
                    "tag": "p",
                    "text": "長尾猫のラクリマを象ったブローチ"
                },
                {
                    "tag": "p",
                    "text": "落下ダメージを完全になくす ただし、落下死亡を防ぐことはできない"
                },
                {
                    "tag": "p",
                    "text": "それは、レアルカリアのお伽話に登場する 大鐘楼に遊ぶ妖精猫である"
                }
            ]
        },
        {
            "tag": "h3",
            "text": "シャブリリの禍",
            "id": "6050",
            "children": [
                {
                    "tag": "p",
                    "text": "目を潰された狂気の肖像 媚びるような薄笑いを浮かべている"
                },
                {
                    "tag": "p",
                    "text": "敵に狙われやすくなる"
                },
                {
                    "tag": "p",
                    "text": "シャブリリという名のその男は 讒言の罰として、人々に瞳を潰されやがてそこに、狂い火の病を宿したという"
                }
            ]
        },
        {
            "tag": "h3",
            "text": "デーディカの禍",
            "id": "6060",
            "children": [
                {
                    "tag": "p",
                    "text": "皮膚を剥がされた狂気の肖像 慈しみの薄笑いを浮かべている"
                },
                {
                    "tag": "p",
                    "text": "被ダメージが増える"
                },
                {
                    "tag": "p",
                    "text": "デーディカという名のその女は あらゆる不義、姦通を行い無数の異形の子をなしたという"
                }
            ]
        },
        {
            "tag": "h3",
            "text": "犠牲の細枝",
            "id": "6070",
            "children": [
                {
                    "tag": "p",
                    "text": "折れそうに細い、枯れ枝のタリスマン"
                },
                {
                    "tag": "p",
                    "text": "死亡時にルーンを落とさず 替わりに、このタリスマンが失われる"
                },
                {
                    "tag": "p",
                    "text": "それは、古い時代に枝打ちされた 黄金樹の一部であるという"
                }
            ]
        },
        {
            "tag": "h3",
            "text": "鉤指の偽装鏡",
            "id": "6080",
            "children": [
                {
                    "tag": "p",
                    "text": "金色の人影を写す、小さな曇り鏡"
                },
                {
                    "tag": "p",
                    "text": "鉤指の主と同様の見た目となる"
                },
                {
                    "tag": "p",
                    "text": "侵入者を欺くために作られた 褪せ人の呪具のひとつ"
                }
            ]
        },
        {
            "tag": "h3",
            "text": "主の偽装鏡",
            "id": "6090",
            "children": [
                {
                    "tag": "p",
                    "text": "生身の人影を写す、小さな曇り鏡"
                },
                {
                    "tag": "p",
                    "text": "召喚された協力者と同様の見た目となる"
                },
                {
                    "tag": "p",
                    "text": "侵入者を欺くために作られた 褪せ人の呪具のひとつ"
                }
            ]
        },
        {
            "tag": "h3",
            "text": "絡み合う臍帯",
            "id": "6100",
            "children": [
                {
                    "tag": "p",
                    "text": "奇妙に歪んだ神秘的な円環 立ち振舞いが変化する"
                }
            ]
        },
        {
            "tag": "h3",
            "text": "祖霊の角",
            "id": "6110",
            "children": [
                {
                    "tag": "p",
                    "text": "祖霊の王の角を切り取ったもの"
                },
                {
                    "tag": "p",
                    "text": "敵を倒したとき、ＦＰを回復する"
                },
                {
                    "tag": "p",
                    "text": "倒れた王の角を苗床に 幾つもの若芽が開き、光を放っているそれは、死から芽吹いた命であり 死から力を得る"
                }
            ]
        }
    ]
}